moderage/__init__.py
moderage/experiment.py
moderage/service.py
moderage/clients/__init__.py
moderage/clients/client.py
moderage/clients/local.py
moderage/clients/server.py
tests/__init__.py
tests/files_test.py
tests/parents_test.py
tests/storage_test.py
moderage_python-0.2.6.dist-info/METADATA
moderage_python-0.2.6.dist-info/WHEEL
moderage_python-0.2.6.dist-info/top_level.txt
moderage_python-0.2.6.dist-info/RECORD
