Metadata-Version: 2.1
Name: moderage-python
Version: 0.2.6
Summary: Mode Rage python client
Home-page: https://gitlab.com/chrisbam4d/moderage-python-client
Author: Chri Bamford
Author-email: chrisbam4d@gmail.com
License: UNKNOWN
Platform: UNKNOWN
Classifier: Programming Language :: Python :: 3
Classifier: License :: OSI Approved :: GNU General Public License v3 (GPLv3)
Classifier: Operating System :: OS Independent
Requires-Dist: requests (==2.21.0)
Requires-Dist: python-magic (==0.4.15)
Requires-Dist: requests-toolbelt (==0.9.1)
Requires-Dist: tqdm (==4.31.1)
Requires-Dist: tinydb (==3.13.0)
Requires-Dist: PyYAML (>=3.2)
